ssl_labs_screenshot/__init__.py
ssl_labs_screenshot/__main__.py
ssl_labs_screenshot-1.0.9.dist-info/LICENSE.txt
ssl_labs_screenshot-1.0.9.dist-info/METADATA
ssl_labs_screenshot-1.0.9.dist-info/WHEEL
ssl_labs_screenshot-1.0.9.dist-info/entry_points.txt
ssl_labs_screenshot-1.0.9.dist-info/top_level.txt
ssl_labs_screenshot-1.0.9.dist-info/RECORD
