Metadata-Version: 2.1
Name: ssl-labs-screenshot
Version: 1.0.9
Summary: A Python package to capture a trimmed screenshot of the SSL Labs report for a given domain.
Author-email: Mark Sowell <mark@marksowell.com>
License: MIT
Project-URL: Source, https://github.com/marksowell/ssl-labs-screenshot
Keywords: ssl,screenshot,ssllabs
Requires-Python: >=3.6
License-File: LICENSE.txt
Requires-Dist: selenium (>=3.141.0)
Requires-Dist: Pillow (>=8.3.2)
